CHANGES.txt
COPYRIGHT.txt
CREDITS.txt
LICENSE.txt
TODO.txt
bootstrap.py
buildout.cfg
setup.py
src/z3c/__init__.py
src/z3c.schema2xml.egg-info/PKG-INFO
src/z3c.schema2xml.egg-info/SOURCES.txt
src/z3c.schema2xml.egg-info/dependency_links.txt
src/z3c.schema2xml.egg-info/entry_points.txt
src/z3c.schema2xml.egg-info/namespace_packages.txt
src/z3c.schema2xml.egg-info/not-zip-safe
src/z3c.schema2xml.egg-info/requires.txt
src/z3c.schema2xml.egg-info/top_level.txt
src/z3c/schema2xml/README.txt
src/z3c/schema2xml/__init__.py
src/z3c/schema2xml/_schema2xml.py
src/z3c/schema2xml/configure.zcml
src/z3c/schema2xml/ftesting.zcml
src/z3c/schema2xml/testing.py
src/z3c/schema2xml/tests.py