Metadata-Version: 1.0
Name: z3c.schema2xml
Version: 1.0
Summary: Convert schema-described Zope 3 objects to XML and back
Home-page: UNKNOWN
Author: Martijn Faassen, Jan-Wijbrand Kolman
Author-email: faassen@startifact.com
License: ZPL
Platform: UNKNOWN
